odinweb/__init__.py
odinweb/flask.py
odinweb.flask-0.5.2.dist-info/DESCRIPTION.rst
odinweb.flask-0.5.2.dist-info/METADATA
odinweb.flask-0.5.2.dist-info/RECORD
odinweb.flask-0.5.2.dist-info/WHEEL
odinweb.flask-0.5.2.dist-info/metadata.json
odinweb.flask-0.5.2.dist-info/pbr.json
odinweb.flask-0.5.2.dist-info/top_level.txt
