Metadata-Version: 2.0
Name: odinweb.flask
Version: 0.5.2
Summary: Toolkit for building web API's using Odin and Flask.
Home-page: https://github.com/python-odin/odinweb.flask
Author: Tim Savage
Author-email: tim@savage.company
License: BSD
Keywords: web
Requires-Dist: odinweb (>=0.5)
Requires-Dist: flask
